qililab/__init__.py
qililab/_optionals.py
qililab/about.py
qililab/constants.py
qililab/data_management.py
qililab/execute_circuit.py
qililab/py.typed
qililab/qililab_settings.py
qililab/slurm.py
qililab/yaml.py
qililab/analog/__init__.py
qililab/analog/annealing_program.py
qililab/analog/fluqe_parameter.py
qililab/analog/one_qubit_transpiler.py
qililab/calibration/__init__.py
qililab/calibration/calibration_controller.py
qililab/calibration/calibration_node.py
qililab/config/__init__.py
qililab/config/config.py
qililab/digital/__init__.py
qililab/digital/circuit_optimizer.py
qililab/digital/circuit_router.py
qililab/digital/circuit_to_pulses.py
qililab/digital/circuit_transpiler.py
qililab/digital/gate_decompositions.py
qililab/digital/native_gates.py
qililab/exceptions/__init__.py
qililab/exceptions/data_unavailable.py
qililab/exceptions/exception_group.py
qililab/exceptions/variable_allocated.py
qililab/extra/__init__.py
qililab/extra/quantum_machines/__init__.py
qililab/extra/quantum_machines/__init__.pyi
qililab/extra/quantum_machines/runtime.py
qililab/extra/quantum_machines/runtime.pyi
qililab/extra/quantum_machines/instrument_controllers/__init__.py
qililab/extra/quantum_machines/instrument_controllers/__init__.pyi
qililab/extra/quantum_machines/instrument_controllers/quantum_machines_cluster_controller.py
qililab/extra/quantum_machines/instruments/__init__.py
qililab/extra/quantum_machines/instruments/__init__.pyi
qililab/extra/quantum_machines/instruments/quantum_machines_cluster.py
qililab/extra/quantum_machines/qprogram/__init__.py
qililab/extra/quantum_machines/qprogram/__init__.pyi
qililab/extra/quantum_machines/qprogram/quantum_machines_compiler.py
qililab/extra/quantum_machines/result/__init__.py
qililab/extra/quantum_machines/result/qprogram/__init__.py
qililab/extra/quantum_machines/result/qprogram/__init__.pyi
qililab/extra/quantum_machines/result/qprogram/quantum_machines_measurement_result.py
qililab/instrument_connections/__init__.py
qililab-0.31.0.dist-info/METADATA
qililab-0.31.0.dist-info/WHEEL
qililab-0.31.0.dist-info/licenses/LICENSE
qililab-0.31.0.dist-info/RECORD
