Metadata-Version: 2.4
Name: qililab
Version: 0.31.0
Summary: Fundamental package for fast characterization and calibration of quantum chips.
Project-URL: Repository, https://github.com/qilimanjaro-tech/qililab
Author-email: Qilimanjaro Quantum Tech <info@qilimanjaro.tech>
License-File: LICENSE
Keywords: quantum control
Classifier: Development Status :: 5 - Production/Stable
Classifier: Environment :: Console
Classifier: Intended Audience :: Developers
Classifier: Intended Audience :: Science/Research
Classifier: License :: OSI Approved :: Apache Software License
Classifier: Operating System :: POSIX :: Linux
Classifier: Programming Language :: Python :: 3
Classifier: Programming Language :: Python :: 3.10
Classifier: Programming Language :: Python :: 3.11
Classifier: Programming Language :: Python :: 3.12
Classifier: Programming Language :: Python :: 3.13
Classifier: Topic :: Scientific/Engineering
Classifier: Topic :: Scientific/Engineering :: Physics
Requires-Python: >=3.10
Requires-Dist: dash>=3.0.2
Requires-Dist: dill>=0.3.9
Requires-Dist: h5py>=3.13.0
Requires-Dist: networkx>=3.4.2
Requires-Dist: pandas==1.5.3
Requires-Dist: papermill>=2.6.0
Requires-Dist: psycopg2-binary>=2.9.10
Requires-Dist: pydantic-settings>=2.11.0
Requires-Dist: pyvisa-py>=0.7.2
Requires-Dist: qblox-instruments==0.16.0
Requires-Dist: qcodes-contrib-drivers>=0.23.0
Requires-Dist: qcodes>=0.51.0
Requires-Dist: qibo==0.2.15
Requires-Dist: qpysequence>=0.10.8
Requires-Dist: rich>=14.0.0
Requires-Dist: ruamel-yaml>=0.18.10
Requires-Dist: sqlalchemy>=2.0.40
Requires-Dist: submitit>=1.5.2
Requires-Dist: tqdm>=4.67.1
Requires-Dist: urllib3>=2.3.0
Requires-Dist: xarray>=2024.3.0
Provides-Extra: quantum-machines
Requires-Dist: qm-qua==1.2.1; extra == 'quantum-machines'
Requires-Dist: qualang-tools>=0.19.3; extra == 'quantum-machines'
